sy_riskmodels/__init__.py
sy_riskmodels/detector.py
sy_riskmodels/evaluate.py
sy_riskmodels/logging.py
sy_riskmodels/models.py
sy_riskmodels/rule.py
sy_riskmodels/scorecard.py
sy_riskmodels/utils.py
sy_riskmodels/contrib/__init__.py
sy_riskmodels/contrib/build_scorecard.py
sy_riskmodels/contrib/var_select.py
sy_riskmodels-0.0.8.dist-info/LICENSE
sy_riskmodels-0.0.8.dist-info/METADATA
sy_riskmodels-0.0.8.dist-info/WHEEL
sy_riskmodels-0.0.8.dist-info/top_level.txt
sy_riskmodels-0.0.8.dist-info/RECORD
