Metadata-Version: 2.1
Name: sy_riskmodels
Version: 0.0.8
Summary: 信用风险模型工具包
Author-email: YAO Siyuan <siyuan89@163.com>
Project-URL: Homepage, https://github.com/siyuany/riskmodels
Project-URL: Bug Tracker, https://github.com/siyuany/riskmodels/issues
Classifier: Programming Language :: Python :: 3
Classifier: License :: OSI Approved :: MIT License
Classifier: Operating System :: OS Independent
Requires-Python: >=3.6
License-File: LICENSE
